Metadata-Version: 2.1
Name: phevaluator
Version: 0.5.3
Summary: PH Evaluator - an efficient Poker Hand Evaluator based on a Perfect Hash algorithm
Home-page: https://github.com/HenryRLee/PokerHandEvaluator/
Author: Henry Lee
Author-email: lee0906@hotmail.com
License: Apache License, Version 2.0
Project-URL: Bug Tracker, https://github.com/HenryRLee/PokerHandEvaluator/issues
Project-URL: Documentation, https://github.com/HenryRLee/PokerHandEvaluator/tree/master/Documentation
Project-URL: Source, https://github.com/HenryRLee/PokerHandEvaluator/tree/master/python
Keywords: poker,texas-holdem,poker-evaluator
Classifier: Development Status :: 3 - Alpha
Classifier: Intended Audience :: Developers
Classifier: License :: OSI Approved :: Apache Software License
Classifier: Topic :: Software Development :: Libraries
Classifier: Programming Language :: Python :: 3
Classifier: Programming Language :: Python :: 3.7
Classifier: Programming Language :: Python :: 3.8
Classifier: Programming Language :: Python :: 3.9
Classifier: Programming Language :: Python :: 3.10
Classifier: Programming Language :: Python :: 3.11
Classifier: Programming Language :: Python :: 3 :: Only
Requires-Python: <4,>=3.7
Requires-Dist: numpy
